mcp_sql_server/.python-version
mcp_sql_server/__init__.py
mcp_sql_server/__main__.py
mcp_sql_server/server.py
mcp_sql_server-0.1.0.dist-info/METADATA
mcp_sql_server-0.1.0.dist-info/WHEEL
mcp_sql_server-0.1.0.dist-info/entry_points.txt
mcp_sql_server-0.1.0.dist-info/licenses/LICENSE
mcp_sql_server-0.1.0.dist-info/RECORD
