Metadata-Version: 2.4
Name: mcp-sql-server
Version: 0.1.0
Summary: A read-only MCP server for interacting with MySQL databases.
Project-URL: Homepage, https://github.com/vivekpathania/ai-experiments/tree/main/mcp
Project-URL: Bug Tracker, https://github.com/vivekpathania/ai-experiments/issues
Author-email: Vivek Pathania <vickypathania@gmail.com>
License: MIT License
License-File: LICENSE
Keywords: database,llm,mcp,mysql,server,sql
Classifier: Development Status :: 3 - Alpha
Classifier: Intended Audience :: Developers
Classifier: License :: OSI Approved :: MIT License
Classifier: Programming Language :: Python :: 3.13
Classifier: Topic :: Database
Classifier: Topic :: Software Development :: Libraries
Requires-Python: >=3.10
Requires-Dist: mcp[cli]>=1.6.0
Requires-Dist: pymysql>=1.1.1
